setup.cfg
setup.py
cetus/__init__.py
cetus/types.py
cetus/utils.py
cetus.egg-info/PKG-INFO
cetus.egg-info/SOURCES.txt
cetus.egg-info/dependency_links.txt
cetus.egg-info/requires.txt
cetus.egg-info/top_level.txt
cetus/data_access/__init__.py
cetus/data_access/connectors.py
cetus/data_access/deletion.py
cetus/data_access/execution.py
cetus/data_access/reading.py
cetus/data_access/saving.py
cetus/data_access/updating.py
cetus/data_access/utils.py
cetus/queries/__init__.py
cetus/queries/deletion.py
cetus/queries/filters.py
cetus/queries/reading.py
cetus/queries/saving.py
cetus/queries/updating.py
cetus/queries/utils.py
cetus/sqlalchemy/__init__.py
cetus/sqlalchemy/query.py
tests/__init__.py
tests/conftest.py
tests/utils.py
tests/data_access_tests/__init__.py
tests/data_access_tests/test_deletion.py
tests/data_access_tests/test_reading.py
tests/data_access_tests/test_saving.py
tests/data_access_tests/test_transaction.py
tests/data_access_tests/test_updating.py
tests/data_access_tests/test_utils.py
tests/fixtures/__init__.py
tests/fixtures/data_access.py
tests/fixtures/records.py
tests/fixtures/tables.py
tests/queries_tests/__init__.py
tests/queries_tests/test_filters.py
tests/strategies/__init__.py
tests/strategies/data_access.py
tests/strategies/filters.py
tests/strategies/records.py
tests/strategies/tables.py
tests/strategies/utils.py