Metadata-Version: 1.1
Name: cetus
Version: 0.9.1
Summary: asynchronous working with PostgreSQL/MySQL based on asyncpg/aiomysql
Home-page: https://github.com/lycantropos/cetus
Author: Azat Ibrakov
Author-email: azatibrakov@gmail.com
License: UNKNOWN
Download-URL: https://github.com/lycantropos/cetus/archive/master.tar.gz
Keywords: async,postgresql,mysql
Platform: UNKNOWN
